piestore/__init__.py
piestore/__version__.py
piestore/api.py
piestore-0.0.2.dist-info/LICENSE
piestore-0.0.2.dist-info/METADATA
piestore-0.0.2.dist-info/WHEEL
piestore-0.0.2.dist-info/top_level.txt
piestore-0.0.2.dist-info/RECORD
